{"frames":{"Player2ShootRight0.png":{"frame":{"x":0,"y":0,"w":168,"h":266},"rotated":false,"trimmed":false,"spriteSourceSize":{"x":0,"y":0,"w":168,"h":266},"sourceSize":{"w":168,"h":266}},"Player2ShootRight1.png":{"frame":{"x":168,"y":0,"w":168,"h":266},"rotated":false,"trimmed":false,"spriteSourceSize":{"x":0,"y":0,"w":168,"h":266},"sourceSize":{"w":168,"h":266}},"Player2ShootRight2.png":{"frame":{"x":336,"y":0,"w":168,"h":266},"rotated":false,"trimmed":false,"spriteSourceSize":{"x":0,"y":0,"w":168,"h":266},"sourceSize":{"w":168,"h":266}},"Player2ShootRight3.png":{"frame":{"x":504,"y":0,"w":168,"h":266},"rotated":false,"trimmed":false,"spriteSourceSize":{"x":0,"y":0,"w":168,"h":266},"sourceSize":{"w":168,"h":266}},"Player2ShootRight4.png":{"frame":{"x":0,"y":266,"w":168,"h":266},"rotated":false,"trimmed":false,"spriteSourceSize":{"x":0,"y":0,"w":168,"h":266},"sourceSize":{"w":168,"h":266}},"Player2ShootRight5.png":{"frame":{"x":168,"y":266,"w":168,"h":266},"rotated":false,"trimmed":false,"spriteSourceSize":{"x":0,"y":0,"w":168,"h":266},"sourceSize":{"w":168,"h":266}},"Player2ShootRight6.png":{"frame":{"x":336,"y":266,"w":168,"h":266},"rotated":false,"trimmed":false,"spriteSourceSize":{"x":0,"y":0,"w":168,"h":266},"sourceSize":{"w":168,"h":266}},"Player2ShootRight7.png":{"frame":{"x":504,"y":266,"w":168,"h":266},"rotated":false,"trimmed":false,"spriteSourceSize":{"x":0,"y":0,"w":168,"h":266},"sourceSize":{"w":168,"h":266}}},"meta":{"app":"https://github.com/piskelapp/piskel/","version":"1.0","image":"Player2ShootRight.png","format":"RGBA8888","size":{"w":672,"h":532}}}